scinode/__init__.py
scinode/nodetree.py
scinode/version.py
scinode/app/__init__.py
scinode/app/app.py
scinode/app/db.py
scinode/app/init_data.py
scinode/app/blueprints/__init__.py
scinode/app/blueprints/component/__init__.py
scinode/app/blueprints/component/component.py
scinode/app/blueprints/component/utils.py
scinode/app/blueprints/component/templates/component_editor.html
scinode/app/blueprints/component/templates/component_exporter.html
scinode/app/blueprints/component/templates/component_importer.html
scinode/app/blueprints/component/templates/component_table.html
scinode/app/blueprints/config/__init__.py
scinode/app/blueprints/config/config.py
scinode/app/blueprints/config/templates/config.html
scinode/app/blueprints/config/templates/daemon_logfile.html
scinode/app/blueprints/data/__init__.py
scinode/app/blueprints/data/data.py
scinode/app/blueprints/data/templates/data_table.html
scinode/app/blueprints/data/templates/data_viewer.html
scinode/app/blueprints/node/__init__.py
scinode/app/blueprints/node/node.py
scinode/app/blueprints/node/templates/__init__.py
scinode/app/blueprints/node/templates/node_table.html
scinode/app/blueprints/node/templates/node_viewer.html
scinode/app/blueprints/nodetree/__init__.py
scinode/app/blueprints/nodetree/nodetree.py
scinode/app/blueprints/nodetree/utils.py
scinode/app/blueprints/nodetree/templates/nodetree_editor.html
scinode/app/blueprints/nodetree/templates/nodetree_exporter.html
scinode/app/blueprints/nodetree/templates/nodetree_importer.html
scinode/app/blueprints/nodetree/templates/nodetree_table.html
scinode/app/blueprints/nodetree/templates/nodetree_viewer.html
scinode/app/blueprints/nodetree/templates/tab-description.html
scinode/app/blueprints/nodetree/templates/tab-graph-sidebar.html
scinode/app/blueprints/nodetree/templates/tab-graph.html
scinode/app/blueprints/nodetree/templates/tab-table.html
scinode/app/blueprints/nodetree/templates/tab.html
scinode/app/blueprints/scheduler/__init__.py
scinode-0.3.7.dist-info/LICENSE
scinode-0.3.7.dist-info/METADATA
scinode-0.3.7.dist-info/WHEEL
scinode-0.3.7.dist-info/entry_points.txt
scinode-0.3.7.dist-info/top_level.txt
scinode-0.3.7.dist-info/RECORD
