Metadata-Version: 2.1
Name: scinode
Version: 0.3.7
Summary: Design computational workflow using nodes.
Home-page: https://github.com/scinode/scinode
Author: Xing Wang
Author-email: xingwang1991@gmail.com
License: MIT License
Requires-Python: >=3.6
License-File: LICENSE
Requires-Dist: psutil
Requires-Dist: numpy
Requires-Dist: scipy
Requires-Dist: click
Requires-Dist: dnspython
Requires-Dist: pymongo
Requires-Dist: mongoengine
Requires-Dist: pandas
Requires-Dist: pyyaml
Requires-Dist: colorama
Requires-Dist: termcolor
Requires-Dist: ipython
Requires-Dist: blinker
Requires-Dist: flask
Requires-Dist: gunicorn
Requires-Dist: cloudpickle
Requires-Dist: disk-objectstore
Requires-Dist: paramiko
Requires-Dist: celery
Provides-Extra: celery
Requires-Dist: celery ; extra == 'celery'
Requires-Dist: gevent ; extra == 'celery'
